datatyping/__init__.py
datatyping/datatyping.py
datatyping/printer.py
datatyping-0.6.0.dist-info/METADATA
datatyping-0.6.0.dist-info/RECORD
datatyping-0.6.0.dist-info/WHEEL
datatyping-0.6.0.dist-info/top_level.txt
