Metadata-Version: 2.1
Name: datatyping
Version: 0.6.0
Summary: Pythonic type checking
Home-page: https://github.com/Zaab1t/datatyping
Author: Carl Bordum Hansen
Author-email: carl@bordum.dk
License: MIT
Keywords: safe data validation typing type check
Platform: UNKNOWN
